CHANGES.txt
DEPENDENCES.txt
README.txt
setup.py
src/ng/__init__.py
src/ng.zcmljunction.egg-info/PKG-INFO
src/ng.zcmljunction.egg-info/SOURCES.txt
src/ng.zcmljunction.egg-info/dependency_links.txt
src/ng.zcmljunction.egg-info/namespace_packages.txt
src/ng.zcmljunction.egg-info/not-zip-safe
src/ng.zcmljunction.egg-info/requires.txt
src/ng.zcmljunction.egg-info/top_level.txt
src/ng/zcmljunction/__init__.py
src/ng/zcmljunction/junction.py
src/ng/zcmljunction/meta.zcml
src/ng/zcmljunction/metaconfigure.py
src/ng/zcmljunction/metadirectives.py
src/ng/zcmljunction/ng.zcmljunction.txt
src/ng/zcmljunction/etc/ng.zcmljunction-meta.zcml
