Metadata-Version: 1.0
Name: ng.zcmljunction
Version: 1.0.3
Summary: Multipurpose adapter used to rewrite attributes input interface into output
Home-page: http://www.dreambot.ru/product/DreamBotZope3Releases/ng.zcmljunction
Author: Andrey Orlov
Author-email: dbdt@dreambot.ru
License: GPL v2.1
Platform: UNKNOWN
Classifier: Environment :: Web Environment
Classifier: Intended Audience :: Developers
Classifier: License :: OSI Approved :: GNU General Public License (GPL)
Classifier: Programming Language :: Python
Classifier: Operating System :: OS Independent
Classifier: Topic :: Internet :: WWW/HTTP
Classifier: Framework :: Zope3
